__init__.py
load.py
run.py
testsolar_unittest/__init__.py
testsolar_unittest/collector.py
testsolar_unittest/executor.py
testsolar_unittest-0.1.2.dist-info/METADATA
testsolar_unittest-0.1.2.dist-info/WHEEL
testsolar_unittest-0.1.2.dist-info/top_level.txt
testsolar_unittest-0.1.2.dist-info/RECORD
